html_test_report/__init__.py
html_test_report/color_text.py
html_test_report/django.py
html_test_report/html_test.py
html_test_report/nose_plugin.py
html_test_report/runner.py
html_test_report/templates/test-case.html
html_test_report-1.0.0.dist-info/LICENSE
html_test_report-1.0.0.dist-info/METADATA
html_test_report-1.0.0.dist-info/WHEEL
html_test_report-1.0.0.dist-info/entry_points.txt
html_test_report-1.0.0.dist-info/top_level.txt
html_test_report-1.0.0.dist-info/RECORD
