Metadata-Version: 2.1
Name: html-test-report
Version: 1.0.0
Summary: Python unittest runner with html report.
Home-page: https://github.com/adelplanque/html-test-report
License: UNKNOWN
Platform: UNKNOWN
Classifier: Development Status :: 4 - Beta
Classifier: Programming Language :: Python :: 2.7
Classifier: Programming Language :: Python :: 3
Classifier: License :: OSI Approved :: MIT License
Classifier: Intended Audience :: Developers
Classifier: Topic :: Software Development :: Testing
Requires-Dist: jinja2
Requires-Dist: pygments
Requires-Dist: six
